ctc_chroma/__init__.py
ctc_chroma/features.py
ctc_chroma/models.py
ctc_chroma/models/model_v1_ctc_train1234valid5.data-00000-of-00001
ctc_chroma/models/model_v1_ctc_train1234valid5.index
ctc_chroma/models/model_v1_ctc_train123valid4.data-00000-of-00001
ctc_chroma/models/model_v1_ctc_train123valid4.index
ctc_chroma/models/model_v1_ctc_train2345valid1.data-00000-of-00001
ctc_chroma/models/model_v1_ctc_train2345valid1.index
ctc_chroma/models/model_v1_ctc_train234valid5.data-00000-of-00001
ctc_chroma/models/model_v1_ctc_train234valid5.index
ctc_chroma/models/model_v1_ctc_train3451valid2.data-00000-of-00001
ctc_chroma/models/model_v1_ctc_train3451valid2.index
ctc_chroma/models/model_v1_ctc_train345valid1.data-00000-of-00001
ctc_chroma/models/model_v1_ctc_train345valid1.index
ctc_chroma/models/model_v1_ctc_train4512valid3.data-00000-of-00001
ctc_chroma/models/model_v1_ctc_train4512valid3.index
ctc_chroma/models/model_v1_ctc_train451valid2.data-00000-of-00001
ctc_chroma/models/model_v1_ctc_train451valid2.index
ctc_chroma/models/model_v1_ctc_train5123valid4.data-00000-of-00001
ctc_chroma/models/model_v1_ctc_train5123valid4.index
ctc_chroma/models/model_v1_ctc_train512valid3.data-00000-of-00001
ctc_chroma/models/model_v1_ctc_train512valid3.index
ctc_chroma/models/model_v2_ctc_train123valid4.data-00000-of-00001
ctc_chroma/models/model_v2_ctc_train123valid4.index
ctc_chroma/models/model_v2_ctc_train234valid5.data-00000-of-00001
ctc_chroma/models/model_v2_ctc_train234valid5.index
ctc_chroma/models/model_v2_ctc_train345valid1.data-00000-of-00001
ctc_chroma/models/model_v2_ctc_train345valid1.index
ctc_chroma/models/model_v2_ctc_train451valid2.data-00000-of-00001
ctc_chroma/models/model_v2_ctc_train451valid2.index
ctc_chroma/models/model_v2_ctc_train512valid3.data-00000-of-00001
ctc_chroma/models/model_v2_ctc_train512valid3.index
ctc_chroma/models/model_v2_linear_train123valid4.data-00000-of-00001
ctc_chroma/models/model_v2_linear_train123valid4.index
ctc_chroma-2.1.dist-info/LICENSE
ctc_chroma-2.1.dist-info/METADATA
ctc_chroma-2.1.dist-info/WHEEL
ctc_chroma-2.1.dist-info/top_level.txt
ctc_chroma-2.1.dist-info/RECORD
