Metadata-Version: 2.1
Name: ctc-chroma
Version: 2.1
Summary: CTC-based chroma feature exractors
Home-page: https://github.com/fzalkow/ctc_chroma
Author: Frank Zalkow
Author-email: frank.zalkow@audiolabs-erlangen.de
License: MIT
Keywords: audio music sound
Platform: UNKNOWN
Classifier: License :: OSI Approved :: MIT License
Classifier: Topic :: Multimedia :: Sound/Audio :: Analysis
Classifier: Programming Language :: Python :: 3
Requires-Python: >=3.6
Requires-Dist: numpy (==1.16.*)
Requires-Dist: scipy (==1.*)
Requires-Dist: matplotlib (==2.0.*)
Requires-Dist: ipython (==7.7.*)
Requires-Dist: jupyter (==1.0.*)
Requires-Dist: tqdm (==4.36.*)
Requires-Dist: numba (==0.48.*)
Requires-Dist: librosa (==0.7.*)
Requires-Dist: tensorflow (==2.*)
